litemon/__init__.py
litemon/client/__init__.py
litemon/client/client.py
litemon/client/metrics_buffer.py
litemon/client/monitor.py
litemon/server/__init__.py
litemon/server/__main__.py
litemon/server/app.py
litemon/server/metrics_store.py
litemon-0.2.0.dist-info/licenses/LICENSE
litemon-0.2.0.dist-info/METADATA
litemon-0.2.0.dist-info/WHEEL
litemon-0.2.0.dist-info/entry_points.txt
litemon-0.2.0.dist-info/top_level.txt
litemon-0.2.0.dist-info/RECORD
