Metadata-Version: 2.4
Name: litemon
Version: 0.2.0
Summary: LiteMon — A lightweight Python function monitoring tool with live metrics.
Author-email: Habeb Nawatha <habeb.naw@gmail.com>
License: MIT
Keywords: monitoring,metrics,decorator,dashboard,python
Classifier: Programming Language :: Python :: 3
Classifier: Operating System :: OS Independent
Classifier: License :: OSI Approved :: MIT License
Classifier: Topic :: Software Development :: Libraries :: Python Modules
Requires-Python: >=3.8
License-File: LICENSE
Requires-Dist: requests>2.20.0
Provides-Extra: dev
Requires-Dist: pytest; extra == "dev"
Requires-Dist: pytest-cov; extra == "dev"
Requires-Dist: requests; extra == "dev"
Requires-Dist: ruff; extra == "dev"
Requires-Dist: flask; extra == "dev"
Requires-Dist: fastapi; extra == "dev"
Requires-Dist: uvicorn; extra == "dev"
Dynamic: license-file
